{
  "changes" : [ {
    "event_info" : {
      "date" : "29/08/2025 13:17:07",
      "sequence" : 700001,
      "date_format" : "dd/mm/rrrr hh24:mi:ss",
      "dml_operation" : "INSERT",
      "table_name" : "OBJETO_SISTEMA",
      "tag_name" : "CMDK",
      "tasy_user" : "lpfreitas",
      "guid" : "6dfddfda-c6ab-488e-a380-82310be8da99"
    },
    "server_info" : {
      "charset" : "AMERICAN_AMERICA.AL32UTF8",
      "database_version" : "19.0",
      "instance_name" : "phcdb4"
    },
    "session_info" : {
      "machine" : "55571289ae56",
      "os_user" : "root",
      "tasy_user" : "lpfreitas"
    },
    "primary_key_values" : [ {
      "column_name" : "NM_OBJETO",
      "data_type" : "VARCHAR2",
      "new_value" : "CMDKLTD_TEST_LUIS",
      "old_value" : null
    }, {
      "column_name" : "IE_BANCO",
      "data_type" : "VARCHAR2",
      "new_value" : "Oracle",
      "old_value" : null
    } ],
    "column_values" : [ {
      "column_name" : "NM_OBJETO",
      "data_type" : "VARCHAR2",
      "new_value" : "CMDKLTD_TEST_LUIS",
      "old_value" : null
    }, {
      "column_name" : "IE_MEMORIA",
      "data_type" : "VARCHAR2",
      "new_value" : "N",
      "old_value" : null
    }, {
      "column_name" : "DT_CRIACAO",
      "data_type" : "DATE",
      "new_value" : "29/08/2025 10:17:07",
      "old_value" : null
    }, {
      "column_name" : "DS_APLICACAO",
      "data_type" : "VARCHAR2",
      "new_value" : "Tasy",
      "old_value" : null
    }, {
      "column_name" : "NM_USUARIO",
      "data_type" : "VARCHAR2",
      "new_value" : "lpfreitas",
      "old_value" : null
    }, {
      "column_name" : "IE_GERAR_SCRIPT",
      "data_type" : "VARCHAR2",
      "new_value" : "S",
      "old_value" : null
    }, {
      "column_name" : "IE_BANCO",
      "data_type" : "VARCHAR2",
      "new_value" : "Oracle",
      "old_value" : null
    }, {
      "column_name" : "IE_TIPO_OBJETO",
      "data_type" : "VARCHAR2",
      "new_value" : "FUNCTION",
      "old_value" : null
    }, {
      "column_name" : "DS_SCRIPT_CRIACAO",
      "data_type" : "LONG",
      "new_value" : "create or replace function CMDKLTD_TEST_LUIS( NR_SCORE_P in Number)\n\t\t\treturn varchar2 is\n\nds_retorno_w\t\tVarchar2(100);\n\nbegin\nds_retorno_w\t:= '';\n\n    if\t(NR_SCORE_P <= 3) then\n\t\tds_retorno_w := obter_desc_expressao(697360);\n\telsif\t(NR_SCORE_P between 3 and 8) then\n\t\tds_retorno_w := obter_desc_expressao(487234);\n\telsif\t(NR_SCORE_P between 9 and 12) then\n\t\tds_retorno_w := obter_desc_expressao(331188);\n    elsif  (NR_SCORE_P between 13 and 15) then\n        ds_retorno_w := obter_desc_expressao(331099);        \n\tend if;\n\nreturn ds_retorno_w;\n\nend CMDKLTD_TEST_LUIS;\n/",
      "old_value" : null
    }, {
      "column_name" : "DT_ATUALIZACAO",
      "data_type" : "DATE",
      "new_value" : "15/05/2025 17:51:12",
      "old_value" : null
    }, {
      "column_name" : "NR_SEQUENCIA",
      "data_type" : "NUMBER",
      "new_value" : 10146319,
      "old_value" : null
    }, {
      "column_name" : "IE_CRIPTOGRAFIA",
      "data_type" : "VARCHAR2",
      "new_value" : "N",
      "old_value" : null
    }, {
      "column_name" : "DS_LAYER",
      "data_type" : "VARCHAR2",
      "new_value" : "CORE.CMDK_LTDA",
      "old_value" : null
    } ]
  }, {
    "event_info" : {
      "date" : "29/08/2025 13:17:07",
      "sequence" : 700002,
      "date_format" : "dd/mm/rrrr hh24:mi:ss",
      "dml_operation" : "DELETE",
      "table_name" : "OBJETO_SISTEMA",
      "tag_name" : "CMDK",
      "tasy_user" : "lpfreitas",
      "guid" : "73384bfc-9ee4-4824-9689-dbb96b337eef"
    },
    "server_info" : {
      "charset" : "AMERICAN_AMERICA.AL32UTF8",
      "database_version" : "19.0",
      "instance_name" : "phcdb4"
    },
    "session_info" : {
      "machine" : "55571289ae56",
      "os_user" : "root",
      "tasy_user" : "lpfreitas"
    },
    "primary_key_values" : [ {
      "column_name" : "NM_OBJETO",
      "data_type" : "VARCHAR2",
      "new_value" : null,
      "old_value" : "CMDKLTD_TEST_LUIS"
    }, {
      "column_name" : "IE_BANCO",
      "data_type" : "VARCHAR2",
      "new_value" : null,
      "old_value" : "Oracle"
    } ],
    "column_values" : [ {
      "column_name" : "NM_OBJETO",
      "data_type" : "VARCHAR2",
      "new_value" : null,
      "old_value" : "CMDKLTD_TEST_LUIS"
    }, {
      "column_name" : "IE_MEMORIA",
      "data_type" : "VARCHAR2",
      "new_value" : null,
      "old_value" : "N"
    }, {
      "column_name" : "DT_CRIACAO",
      "data_type" : "DATE",
      "new_value" : null,
      "old_value" : "29/08/2025 10:17:07"
    }, {
      "column_name" : "DS_APLICACAO",
      "data_type" : "VARCHAR2",
      "new_value" : null,
      "old_value" : "Tasy"
    }, {
      "column_name" : "NM_USUARIO",
      "data_type" : "VARCHAR2",
      "new_value" : null,
      "old_value" : "lpfreitas"
    }, {
      "column_name" : "IE_GERAR_SCRIPT",
      "data_type" : "VARCHAR2",
      "new_value" : null,
      "old_value" : "S"
    }, {
      "column_name" : "IE_BANCO",
      "data_type" : "VARCHAR2",
      "new_value" : null,
      "old_value" : "Oracle"
    }, {
      "column_name" : "IE_TIPO_OBJETO",
      "data_type" : "VARCHAR2",
      "new_value" : null,
      "old_value" : "FUNCTION"
    }, {
      "column_name" : "DS_SCRIPT_CRIACAO",
      "data_type" : "LONG",
      "new_value" : null,
      "old_value" : "create or replace function CMDKLTD_TEST_LUIS( NR_SCORE_P in Number)\n\t\t\treturn varchar2 is\n\nds_retorno_w\t\tVarchar2(100);\n\nbegin\nds_retorno_w\t:= '';\n\n    if\t(NR_SCORE_P <= 3) then\n\t\tds_retorno_w := obter_desc_expressao(697360);\n\telsif\t(NR_SCORE_P between 3 and 8) then\n\t\tds_retorno_w := obter_desc_expressao(487234);\n\telsif\t(NR_SCORE_P between 9 and 12) then\n\t\tds_retorno_w := obter_desc_expressao(331188);\n    elsif  (NR_SCORE_P between 13 and 15) then\n        ds_retorno_w := obter_desc_expressao(331099);        \n\tend if;\n\nreturn ds_retorno_w;\n\nend CMDKLTD_TEST_LUIS;\n/"
    }, {
      "column_name" : "DT_ATUALIZACAO",
      "data_type" : "DATE",
      "new_value" : null,
      "old_value" : "15/05/2025 17:51:12"
    }, {
      "column_name" : "NR_SEQUENCIA",
      "data_type" : "NUMBER",
      "new_value" : null,
      "old_value" : 10146319
    }, {
      "column_name" : "IE_CRIPTOGRAFIA",
      "data_type" : "VARCHAR2",
      "new_value" : null,
      "old_value" : "N"
    }, {
      "column_name" : "DS_LAYER",
      "data_type" : "VARCHAR2",
      "new_value" : null,
      "old_value" : "CORE.CMDK_LTDA"
    } ]
  }, {
    "event_info" : {
      "date" : "29/08/2025 13:17:07",
      "sequence" : 500003,
      "date_format" : "dd/mm/rrrr hh24:mi:ss",
      "dml_operation" : "INSERT",
      "table_name" : "TABELA_SISTEMA",
      "tag_name" : "CMDK",
      "tasy_user" : "srcunha",
      "guid" : "0d62600d-79f9-47f8-a27f-488dfdbb2788"
    },
    "server_info" : {
      "charset" : "AMERICAN_AMERICA.AL32UTF8",
      "database_version" : "19.0",
      "instance_name" : "phcdb4"
    },
    "session_info" : {
      "machine" : "55571289ae56",
      "os_user" : "root",
      "tasy_user" : "lpfreitas"
    },
    "primary_key_values" : [ {
      "column_name" : "NM_TABELA",
      "data_type" : "VARCHAR2",
      "new_value" : "CMDKLTD_ABDFILD_49",
      "old_value" : null
    } ],
    "column_values" : [ {
      "column_name" : "IE_SINCRONIZAR",
      "data_type" : "VARCHAR2",
      "new_value" : "N",
      "old_value" : null
    }, {
      "column_name" : "DS_SHORTNAME",
      "data_type" : "VARCHAR2",
      "new_value" : "ABDFILD6E7",
      "old_value" : null
    }, {
      "column_name" : "DS_TABELA",
      "data_type" : "VARCHAR2",
      "new_value" : "Utilizada como reposit\u00f3rio de dados de defini\u00e7\u00e3o dos campos do cat\u00e1logo do ABDAMED.",
      "old_value" : null
    }, {
      "column_name" : "DS_TABLESPACE_IND",
      "data_type" : "VARCHAR2",
      "new_value" : "TASY_INDEX",
      "old_value" : null
    }, {
      "column_name" : "IE_GERA_DEFINICAO",
      "data_type" : "VARCHAR2",
      "new_value" : "S",
      "old_value" : null
    }, {
      "column_name" : "NM_TABELA",
      "data_type" : "VARCHAR2",
      "new_value" : "CMDKLTD_ABDFILD_49",
      "old_value" : null
    }, {
      "column_name" : "DT_ATUALIZACAO",
      "data_type" : "DATE",
      "new_value" : "25/08/2025 17:39:05",
      "old_value" : null
    }, {
      "column_name" : "DT_CRIACAO",
      "data_type" : "DATE",
      "new_value" : "25/07/2018 16:21:15",
      "old_value" : null
    }, {
      "column_name" : "IE_SITUACAO",
      "data_type" : "VARCHAR2",
      "new_value" : "A",
      "old_value" : null
    }, {
      "column_name" : "QT_MAX_REGISTRO",
      "data_type" : "NUMBER",
      "new_value" : "0",
      "old_value" : null
    }, {
      "column_name" : "QT_REGISTROS_PREVISTO",
      "data_type" : "NUMBER",
      "new_value" : "100",
      "old_value" : null
    }, {
      "column_name" : "QT_FATOR_CONVERSAO",
      "data_type" : "NUMBER",
      "new_value" : "1",
      "old_value" : null
    }, {
      "column_name" : "DS_TABLESPACE_TAB",
      "data_type" : "VARCHAR2",
      "new_value" : "TASY_DATA",
      "old_value" : null
    }, {
      "column_name" : "IE_TIPO_CALCULO",
      "data_type" : "VARCHAR2",
      "new_value" : "R",
      "old_value" : null
    }, {
      "column_name" : "NM_USUARIO",
      "data_type" : "VARCHAR2",
      "new_value" : "srcunha",
      "old_value" : null
    }, {
      "column_name" : "IE_CRIAR_ALTERAR",
      "data_type" : "VARCHAR2",
      "new_value" : "M",
      "old_value" : null
    }, {
      "column_name" : "QT_REGISTROS_ATUAL",
      "data_type" : "NUMBER",
      "new_value" : "100",
      "old_value" : null
    }, {
      "column_name" : "NR_SEQ_MODULO",
      "data_type" : "NUMBER",
      "new_value" : 82,
      "old_value" : null
    }, {
      "column_name" : "IE_RESTRINGE_ESTAB",
      "data_type" : "VARCHAR2",
      "new_value" : "N",
      "old_value" : null
    }, {
      "column_name" : "IE_REGRA_ATRIBUTO",
      "data_type" : "VARCHAR2",
      "new_value" : "S",
      "old_value" : null
    }, {
      "column_name" : "IE_CADASTRO_GERAL",
      "data_type" : "VARCHAR2",
      "new_value" : "M",
      "old_value" : null
    }, {
      "column_name" : "DS_APLICACAO",
      "data_type" : "VARCHAR2",
      "new_value" : "TasySup",
      "old_value" : null
    }, {
      "column_name" : "DS_SQL_LOOKUP",
      "data_type" : "VARCHAR2",
      "new_value" : "",
      "old_value" : null
    }, {
      "column_name" : "IE_TROCA_CAMPO_GRID",
      "data_type" : "VARCHAR2",
      "new_value" : "S",
      "old_value" : null
    }, {
      "column_name" : "IE_RESTRINGE_EMPRESA",
      "data_type" : "VARCHAR2",
      "new_value" : "N",
      "old_value" : null
    }, {
      "column_name" : "QT_MAX_CAMPO",
      "data_type" : "NUMBER",
      "new_value" : "0",
      "old_value" : null
    }, {
      "column_name" : "QT_ALTURA_PANEL",
      "data_type" : "NUMBER",
      "new_value" : "0",
      "old_value" : null
    }, {
      "column_name" : "QT_LARGURA_PANEL",
      "data_type" : "NUMBER",
      "new_value" : "0",
      "old_value" : null
    }, {
      "column_name" : "QT_POS_ESQUERDA",
      "data_type" : "NUMBER",
      "new_value" : "0",
      "old_value" : null
    }, {
      "column_name" : "QT_POS_TOPO",
      "data_type" : "NUMBER",
      "new_value" : "0",
      "old_value" : null
    }, {
      "column_name" : "QT_INTERVALO_CAMPO",
      "data_type" : "NUMBER",
      "new_value" : "0",
      "old_value" : null
    }, {
      "column_name" : "IE_TEMPORARIA",
      "data_type" : "VARCHAR2",
      "new_value" : "N",
      "old_value" : null
    }, {
      "column_name" : "IE_EXPORTAR",
      "data_type" : "VARCHAR2",
      "new_value" : "N",
      "old_value" : null
    }, {
      "column_name" : "IE_REGRA_TABELA",
      "data_type" : "VARCHAR2",
      "new_value" : "N",
      "old_value" : null
    }, {
      "column_name" : "IE_LIMPAR_LOG",
      "data_type" : "VARCHAR2",
      "new_value" : "N",
      "old_value" : null
    }, {
      "column_name" : "DT_ATUALIZACAO_NREC",
      "data_type" : "DATE",
      "new_value" : "25/07/2018 16:21:15",
      "old_value" : null
    }, {
      "column_name" : "NM_USUARIO_NREC",
      "data_type" : "VARCHAR2",
      "new_value" : "srcunha",
      "old_value" : null
    }, {
      "column_name" : "IE_CALLSTACK",
      "data_type" : "VARCHAR2",
      "new_value" : "N",
      "old_value" : null
    }, {
      "column_name" : "CD_EXP_TITULO",
      "data_type" : "NUMBER",
      "new_value" : 0,
      "old_value" : null
    }, {
      "column_name" : "CD_EXP_CADASTRO",
      "data_type" : "NUMBER",
      "new_value" : 888149,
      "old_value" : null
    }, {
      "column_name" : "CD_EXP_TABELA",
      "data_type" : "NUMBER",
      "new_value" : 888151,
      "old_value" : null
    }, {
      "column_name" : "IE_CRIA_LOG_LOCAL",
      "data_type" : "VARCHAR2",
      "new_value" : "",
      "old_value" : null
    }, {
      "column_name" : "DS_LAYER",
      "data_type" : "VARCHAR2",
      "new_value" : "CORE.CMDK_LTDA",
      "old_value" : null
    } ]
  }, {
    "event_info" : {
      "date" : "29/08/2025 13:17:07",
      "sequence" : 500004,
      "date_format" : "dd/mm/rrrr hh24:mi:ss",
      "dml_operation" : "INSERT",
      "table_name" : "TABELA_ATRIBUTO",
      "tag_name" : "CMDK",
      "tasy_user" : "lpfreitas",
      "guid" : "75685c0b-080b-4c5e-8ad6-5e99bcc4d618"
    },
    "server_info" : {
      "charset" : "AMERICAN_AMERICA.AL32UTF8",
      "database_version" : "19.0",
      "instance_name" : "phcdb4"
    },
    "session_info" : {
      "machine" : "55571289ae56",
      "os_user" : "root",
      "tasy_user" : "lpfreitas"
    },
    "primary_key_values" : [ {
      "column_name" : "NM_TABELA",
      "data_type" : "VARCHAR2",
      "new_value" : "CMDKLTD_ABDFILD_49",
      "old_value" : null
    }, {
      "column_name" : "NM_ATRIBUTO",
      "data_type" : "VARCHAR2",
      "new_value" : "C_NR_SEQUENCIA",
      "old_value" : null
    } ],
    "column_values" : [ {
      "column_name" : "NR_SEQUENCIA_CRIACAO",
      "data_type" : "NUMBER",
      "new_value" : 1,
      "old_value" : null
    }, {
      "column_name" : "IE_OBRIGATORIO",
      "data_type" : "VARCHAR2",
      "new_value" : "S",
      "old_value" : null
    }, {
      "column_name" : "NM_USUARIO",
      "data_type" : "VARCHAR2",
      "new_value" : "lpfreitas",
      "old_value" : null
    }, {
      "column_name" : "QT_DECIMAIS",
      "data_type" : "NUMBER",
      "new_value" : 0,
      "old_value" : null
    }, {
      "column_name" : "IE_CRIAR_ALTERAR",
      "data_type" : "VARCHAR2",
      "new_value" : "M",
      "old_value" : null
    }, {
      "column_name" : "IE_SITUACAO",
      "data_type" : "VARCHAR2",
      "new_value" : "A",
      "old_value" : null
    }, {
      "column_name" : "VL_DEFAULT",
      "data_type" : "VARCHAR2",
      "new_value" : "",
      "old_value" : null
    }, {
      "column_name" : "NM_ATRIBUTO",
      "data_type" : "VARCHAR2",
      "new_value" : "C_NR_SEQUENCIA",
      "old_value" : null
    }, {
      "column_name" : "IE_LOG_EXCLUSAO",
      "data_type" : "VARCHAR2",
      "new_value" : "N",
      "old_value" : null
    }, {
      "column_name" : "QT_TAMANHO",
      "data_type" : "NUMBER",
      "new_value" : 10,
      "old_value" : null
    }, {
      "column_name" : "NM_TABELA",
      "data_type" : "VARCHAR2",
      "new_value" : "CMDKLTD_ABDFILD_49",
      "old_value" : null
    }, {
      "column_name" : "CD_DOMINIO",
      "data_type" : "NUMBER",
      "new_value" : 0,
      "old_value" : null
    }, {
      "column_name" : "DT_CRIACAO",
      "data_type" : "DATE",
      "new_value" : "25/07/2018 16:29:34",
      "old_value" : null
    }, {
      "column_name" : "IE_CRIAR_DESCRICAO",
      "data_type" : "VARCHAR2",
      "new_value" : "N",
      "old_value" : null
    }, {
      "column_name" : "NM_ATRIBUTO_PAI",
      "data_type" : "VARCHAR2",
      "new_value" : "",
      "old_value" : null
    }, {
      "column_name" : "QT_SEQ_INICIO",
      "data_type" : "NUMBER",
      "new_value" : 1,
      "old_value" : null
    }, {
      "column_name" : "QT_SEQ_INCREMENTO",
      "data_type" : "NUMBER",
      "new_value" : 1,
      "old_value" : null
    }, {
      "column_name" : "DS_VALORES",
      "data_type" : "VARCHAR2",
      "new_value" : "",
      "old_value" : null
    }, {
      "column_name" : "IE_READONLY",
      "data_type" : "VARCHAR2",
      "new_value" : "N",
      "old_value" : null
    }, {
      "column_name" : "IE_TABSTOP",
      "data_type" : "VARCHAR2",
      "new_value" : "S",
      "old_value" : null
    }, {
      "column_name" : "DT_ATUALIZACAO",
      "data_type" : "DATE",
      "new_value" : "25/08/2025 17:39:06",
      "old_value" : null
    }, {
      "column_name" : "IE_TIPO_ATRIBUTO",
      "data_type" : "VARCHAR2",
      "new_value" : "NUMBER",
      "old_value" : null
    }, {
      "column_name" : "IE_CONVERTE_NEGATIVO",
      "data_type" : "VARCHAR2",
      "new_value" : "N",
      "old_value" : null
    }, {
      "column_name" : "QT_CACHE",
      "data_type" : "NUMBER",
      "new_value" : 0,
      "old_value" : null
    }, {
      "column_name" : "IE_LOG_UPDATE",
      "data_type" : "VARCHAR2",
      "new_value" : "N",
      "old_value" : null
    }, {
      "column_name" : "IE_ATUALIZAR_VERSAO",
      "data_type" : "VARCHAR2",
      "new_value" : "N",
      "old_value" : null
    }, {
      "column_name" : "IE_STATUS",
      "data_type" : "VARCHAR2",
      "new_value" : "N",
      "old_value" : null
    }, {
      "column_name" : "IE_CRIAR_DESC_FK",
      "data_type" : "VARCHAR2",
      "new_value" : "S",
      "old_value" : null
    }, {
      "column_name" : "IE_UNIDADE_MEDIDA",
      "data_type" : "VARCHAR2",
      "new_value" : "S",
      "old_value" : null
    }, {
      "column_name" : "IE_REGRA_UNID_MEDIDA",
      "data_type" : "VARCHAR2",
      "new_value" : "N",
      "old_value" : null
    }, {
      "column_name" : "IE_DBL_CLICK_READONLY",
      "data_type" : "VARCHAR2",
      "new_value" : "N",
      "old_value" : null
    }, {
      "column_name" : "IE_DEFAULT_BANCO",
      "data_type" : "VARCHAR2",
      "new_value" : "N",
      "old_value" : null
    }, {
      "column_name" : "CD_EXP_DESC",
      "data_type" : "NUMBER",
      "new_value" : 557610,
      "old_value" : null
    }, {
      "column_name" : "CD_EXP_VALORES",
      "data_type" : "NUMBER",
      "new_value" : 0,
      "old_value" : null
    }, {
      "column_name" : "NR_SEQ_DIC_OBJETO",
      "data_type" : "NUMBER",
      "new_value" : 0,
      "old_value" : null
    }, {
      "column_name" : "IE_INFORMACAO_SENSIVEL",
      "data_type" : "VARCHAR2",
      "new_value" : "",
      "old_value" : null
    } ]
  }, {
    "event_info" : {
      "date" : "29/08/2025 13:17:07",
      "sequence" : 500005,
      "date_format" : "dd/mm/rrrr hh24:mi:ss",
      "dml_operation" : "INSERT",
      "table_name" : "INDICE",
      "tag_name" : "CMDK",
      "tasy_user" : "lpfreitas",
      "guid" : "d1033ce1-9a7c-403a-9954-51ff7f7d3a52"
    },
    "server_info" : {
      "charset" : "AMERICAN_AMERICA.AL32UTF8",
      "database_version" : "19.0",
      "instance_name" : "phcdb4"
    },
    "session_info" : {
      "machine" : "55571289ae56",
      "os_user" : "root",
      "tasy_user" : "lpfreitas"
    },
    "primary_key_values" : [ {
      "column_name" : "NM_TABELA",
      "data_type" : "VARCHAR2",
      "new_value" : "CMDKLTD_ABDFILD_49",
      "old_value" : null
    }, {
      "column_name" : "NM_INDICE",
      "data_type" : "VARCHAR2",
      "new_value" : "ABDFILD_49_PK",
      "old_value" : null
    } ],
    "column_values" : [ {
      "column_name" : "DS_INDICE",
      "data_type" : "VARCHAR2",
      "new_value" : "Chave prim\u00e1ria",
      "old_value" : null
    }, {
      "column_name" : "IE_TIPO",
      "data_type" : "VARCHAR2",
      "new_value" : "PK",
      "old_value" : null
    }, {
      "column_name" : "NM_USUARIO",
      "data_type" : "VARCHAR2",
      "new_value" : "lpfreitas",
      "old_value" : null
    }, {
      "column_name" : "DT_CRIACAO",
      "data_type" : "DATE",
      "new_value" : "25/07/2018 16:29:36",
      "old_value" : null
    }, {
      "column_name" : "IE_SITUACAO",
      "data_type" : "VARCHAR2",
      "new_value" : "A",
      "old_value" : null
    }, {
      "column_name" : "NM_INDICE",
      "data_type" : "VARCHAR2",
      "new_value" : "ABDFILD_49_PK",
      "old_value" : null
    }, {
      "column_name" : "NM_TABELA",
      "data_type" : "VARCHAR2",
      "new_value" : "CMDKLTD_ABDFILD_49",
      "old_value" : null
    }, {
      "column_name" : "IE_CRIAR_ALTERAR",
      "data_type" : "VARCHAR2",
      "new_value" : "M",
      "old_value" : null
    }, {
      "column_name" : "DT_ATUALIZACAO",
      "data_type" : "DATE",
      "new_value" : "25/08/2025 17:39:06",
      "old_value" : null
    }, {
      "column_name" : "IE_IGNORADO_CLIENTE",
      "data_type" : "VARCHAR2",
      "new_value" : "",
      "old_value" : null
    }, {
      "column_name" : "IE_CLASSIFICACAO",
      "data_type" : "VARCHAR2",
      "new_value" : "IR",
      "old_value" : null
    } ]
  }, {
    "event_info" : {
      "date" : "29/08/2025 13:17:07",
      "sequence" : 500006,
      "date_format" : "dd/mm/rrrr hh24:mi:ss",
      "dml_operation" : "INSERT",
      "table_name" : "INDICE_ATRIBUTO",
      "tag_name" : "CMDK",
      "tasy_user" : "lpfreitas",
      "guid" : "a4ec860e-9bfd-4c73-9f55-e5c7b4be6006"
    },
    "server_info" : {
      "charset" : "AMERICAN_AMERICA.AL32UTF8",
      "database_version" : "19.0",
      "instance_name" : "phcdb4"
    },
    "session_info" : {
      "machine" : "55571289ae56",
      "os_user" : "root",
      "tasy_user" : "lpfreitas"
    },
    "primary_key_values" : [ {
      "column_name" : "NM_TABELA",
      "data_type" : "VARCHAR2",
      "new_value" : "CMDKLTD_ABDFILD_49",
      "old_value" : null
    }, {
      "column_name" : "NM_INDICE",
      "data_type" : "VARCHAR2",
      "new_value" : "ABDFILD_49_PK",
      "old_value" : null
    }, {
      "column_name" : "NR_SEQUENCIA",
      "data_type" : "NUMBER",
      "new_value" : 1,
      "old_value" : null
    } ],
    "column_values" : [ {
      "column_name" : "NM_TABELA",
      "data_type" : "VARCHAR2",
      "new_value" : "CMDKLTD_ABDFILD_49",
      "old_value" : null
    }, {
      "column_name" : "DT_ATUALIZACAO",
      "data_type" : "DATE",
      "new_value" : "25/08/2025 17:39:06",
      "old_value" : null
    }, {
      "column_name" : "NM_INDICE",
      "data_type" : "VARCHAR2",
      "new_value" : "ABDFILD_49_PK",
      "old_value" : null
    }, {
      "column_name" : "NR_SEQUENCIA",
      "data_type" : "NUMBER",
      "new_value" : 1,
      "old_value" : null
    }, {
      "column_name" : "NM_USUARIO",
      "data_type" : "VARCHAR2",
      "new_value" : "lpfreitas",
      "old_value" : null
    }, {
      "column_name" : "NM_ATRIBUTO",
      "data_type" : "VARCHAR2",
      "new_value" : "C_NR_SEQUENCIA",
      "old_value" : null
    }, {
      "column_name" : "DS_INDICE_FUNCTION",
      "data_type" : "VARCHAR2",
      "new_value" : "",
      "old_value" : null
    } ]
  }, {
    "event_info" : {
      "date" : "29/08/2025 13:17:07",
      "sequence" : 500007,
      "date_format" : "dd/mm/rrrr hh24:mi:ss",
      "dml_operation" : "INSERT",
      "table_name" : "INTEGRIDADE_REFERENCIAL",
      "tag_name" : "CMDK",
      "tasy_user" : "lpfreitas",
      "guid" : "83fa185e-a501-40dd-a0d7-b816782243e8"
    },
    "server_info" : {
      "charset" : "AMERICAN_AMERICA.AL32UTF8",
      "database_version" : "19.0",
      "instance_name" : "phcdb4"
    },
    "session_info" : {
      "machine" : "55571289ae56",
      "os_user" : "root",
      "tasy_user" : "lpfreitas"
    },
    "primary_key_values" : [ {
      "column_name" : "NM_TABELA",
      "data_type" : "VARCHAR2",
      "new_value" : "CMDKLTD_ABDFILD_49",
      "old_value" : null
    }, {
      "column_name" : "NM_INTEGRIDADE_REFERENCIAL",
      "data_type" : "VARCHAR2",
      "new_value" : "ABDFILD6E7_ABDFILD_FK",
      "old_value" : null
    } ],
    "column_values" : [ {
      "column_name" : "IE_REGRA_DELECAO",
      "data_type" : "VARCHAR2",
      "new_value" : "CASCADE",
      "old_value" : null
    }, {
      "column_name" : "NM_TABELA",
      "data_type" : "VARCHAR2",
      "new_value" : "CMDKLTD_ABDFILD_49",
      "old_value" : null
    }, {
      "column_name" : "DT_ATUALIZACAO",
      "data_type" : "DATE",
      "new_value" : "25/08/2025 17:39:06",
      "old_value" : null
    }, {
      "column_name" : "DT_CRIACAO",
      "data_type" : "DATE",
      "new_value" : "25/08/2025 17:39:06",
      "old_value" : null
    }, {
      "column_name" : "IE_CRIAR_ALTERAR",
      "data_type" : "VARCHAR2",
      "new_value" : "I",
      "old_value" : null
    }, {
      "column_name" : "IE_SITUACAO",
      "data_type" : "VARCHAR2",
      "new_value" : "A",
      "old_value" : null
    }, {
      "column_name" : "NM_TABELA_REFERENCIA",
      "data_type" : "VARCHAR2",
      "new_value" : "ABDAMED_FIELD",
      "old_value" : null
    }, {
      "column_name" : "NM_USUARIO",
      "data_type" : "VARCHAR2",
      "new_value" : "lpfreitas",
      "old_value" : null
    }, {
      "column_name" : "NM_INTEGRIDADE_REFERENCIAL",
      "data_type" : "VARCHAR2",
      "new_value" : "ABDFILD6E7_ABDFILD_FK",
      "old_value" : null
    } ]
  }, {
    "event_info" : {
      "date" : "29/08/2025 13:17:07",
      "sequence" : 500008,
      "date_format" : "dd/mm/rrrr hh24:mi:ss",
      "dml_operation" : "INSERT",
      "table_name" : "INTEGRIDADE_ATRIBUTO",
      "tag_name" : "CMDK",
      "tasy_user" : "lpfreitas",
      "guid" : "8b37706b-b846-4825-95c4-d4edd2ef8f9e"
    },
    "server_info" : {
      "charset" : "AMERICAN_AMERICA.AL32UTF8",
      "database_version" : "19.0",
      "instance_name" : "phcdb4"
    },
    "session_info" : {
      "machine" : "55571289ae56",
      "os_user" : "root",
      "tasy_user" : "lpfreitas"
    },
    "primary_key_values" : [ {
      "column_name" : "NM_TABELA",
      "data_type" : "VARCHAR2",
      "new_value" : "CMDKLTD_ABDFILD_49",
      "old_value" : null
    }, {
      "column_name" : "NM_INTEGRIDADE_REFERENCIAL",
      "data_type" : "VARCHAR2",
      "new_value" : "ABDFILD6E7_ABDFILD_FK",
      "old_value" : null
    }, {
      "column_name" : "NM_ATRIBUTO",
      "data_type" : "VARCHAR2",
      "new_value" : "C_NR_SEQUENCIA",
      "old_value" : null
    } ],
    "column_values" : [ {
      "column_name" : "NM_ATRIBUTO_REF",
      "data_type" : "VARCHAR2",
      "new_value" : "C_NR_SEQUENCIA",
      "old_value" : null
    }, {
      "column_name" : "NM_TABELA",
      "data_type" : "VARCHAR2",
      "new_value" : "CMDKLTD_ABDFILD_49",
      "old_value" : null
    }, {
      "column_name" : "NM_INTEGRIDADE_REFERENCIAL",
      "data_type" : "VARCHAR2",
      "new_value" : "ABDFILD6E7_ABDFILD_FK",
      "old_value" : null
    }, {
      "column_name" : "NM_ATRIBUTO",
      "data_type" : "VARCHAR2",
      "new_value" : "C_NR_SEQUENCIA",
      "old_value" : null
    }, {
      "column_name" : "DT_ATUALIZACAO",
      "data_type" : "DATE",
      "new_value" : "25/08/2025 17:39:06",
      "old_value" : null
    }, {
      "column_name" : "NM_USUARIO",
      "data_type" : "VARCHAR2",
      "new_value" : "lpfreitas",
      "old_value" : null
    }, {
      "column_name" : "IE_SEQUENCIA_CRIACAO",
      "data_type" : "NUMBER",
      "new_value" : 1,
      "old_value" : null
    } ]
  }, {
    "event_info" : {
      "date" : "29/08/2025 13:17:07",
      "sequence" : 500009,
      "date_format" : "dd/mm/rrrr hh24:mi:ss",
      "dml_operation" : "INSERT",
      "table_name" : "TABELA_SISTEMA",
      "tag_name" : "CMDK",
      "tasy_user" : "srcunha",
      "guid" : "0d875c12-eef6-44bd-bad7-7e9c697cf158"
    },
    "server_info" : {
      "charset" : "AMERICAN_AMERICA.AL32UTF8",
      "database_version" : "19.0",
      "instance_name" : "phcdb4"
    },
    "session_info" : {
      "machine" : "55571289ae56",
      "os_user" : "root",
      "tasy_user" : "lpfreitas"
    },
    "primary_key_values" : [ {
      "column_name" : "NM_TABELA",
      "data_type" : "VARCHAR2",
      "new_value" : "CMDKLTD_AAZFMED_50",
      "old_value" : null
    } ],
    "column_values" : [ {
      "column_name" : "IE_SINCRONIZAR",
      "data_type" : "VARCHAR2",
      "new_value" : "N",
      "old_value" : null
    }, {
      "column_name" : "DS_SHORTNAME",
      "data_type" : "VARCHAR2",
      "new_value" : "AAZFMED6E7",
      "old_value" : null
    }, {
      "column_name" : "DS_TABELA",
      "data_type" : "VARCHAR2",
      "new_value" : "Utilizada como resposit\u00f3rio de dados do arquivo AAZF_MED do cat\u00e1logo do ABDAMED.",
      "old_value" : null
    }, {
      "column_name" : "DS_TABLESPACE_IND",
      "data_type" : "VARCHAR2",
      "new_value" : "TASY_INDEX",
      "old_value" : null
    }, {
      "column_name" : "IE_GERA_DEFINICAO",
      "data_type" : "VARCHAR2",
      "new_value" : "S",
      "old_value" : null
    }, {
      "column_name" : "NM_TABELA",
      "data_type" : "VARCHAR2",
      "new_value" : "CMDKLTD_AAZFMED_50",
      "old_value" : null
    }, {
      "column_name" : "DT_ATUALIZACAO",
      "data_type" : "DATE",
      "new_value" : "25/08/2025 17:39:50",
      "old_value" : null
    }, {
      "column_name" : "DT_CRIACAO",
      "data_type" : "DATE",
      "new_value" : "27/06/2018 09:33:32",
      "old_value" : null
    }, {
      "column_name" : "IE_SITUACAO",
      "data_type" : "VARCHAR2",
      "new_value" : "A",
      "old_value" : null
    }, {
      "column_name" : "QT_MAX_REGISTRO",
      "data_type" : "NUMBER",
      "new_value" : "0",
      "old_value" : null
    }, {
      "column_name" : "QT_REGISTROS_PREVISTO",
      "data_type" : "NUMBER",
      "new_value" : "100",
      "old_value" : null
    }, {
      "column_name" : "QT_FATOR_CONVERSAO",
      "data_type" : "NUMBER",
      "new_value" : "1",
      "old_value" : null
    }, {
      "column_name" : "DS_TABLESPACE_TAB",
      "data_type" : "VARCHAR2",
      "new_value" : "TASY_DATA",
      "old_value" : null
    }, {
      "column_name" : "IE_TIPO_CALCULO",
      "data_type" : "VARCHAR2",
      "new_value" : "R",
      "old_value" : null
    }, {
      "column_name" : "NM_USUARIO",
      "data_type" : "VARCHAR2",
      "new_value" : "lhalves",
      "old_value" : null
    }, {
      "column_name" : "IE_CRIAR_ALTERAR",
      "data_type" : "VARCHAR2",
      "new_value" : "M",
      "old_value" : null
    }, {
      "column_name" : "QT_REGISTROS_ATUAL",
      "data_type" : "NUMBER",
      "new_value" : "100",
      "old_value" : null
    }, {
      "column_name" : "NR_SEQ_MODULO",
      "data_type" : "NUMBER",
      "new_value" : 82,
      "old_value" : null
    }, {
      "column_name" : "IE_RESTRINGE_ESTAB",
      "data_type" : "VARCHAR2",
      "new_value" : "N",
      "old_value" : null
    }, {
      "column_name" : "IE_REGRA_ATRIBUTO",
      "data_type" : "VARCHAR2",
      "new_value" : "S",
      "old_value" : null
    }, {
      "column_name" : "IE_CADASTRO_GERAL",
      "data_type" : "VARCHAR2",
      "new_value" : "M",
      "old_value" : null
    }, {
      "column_name" : "DS_APLICACAO",
      "data_type" : "VARCHAR2",
      "new_value" : "TasySup",
      "old_value" : null
    }, {
      "column_name" : "DS_SQL_LOOKUP",
      "data_type" : "VARCHAR2",
      "new_value" : "",
      "old_value" : null
    }, {
      "column_name" : "IE_TROCA_CAMPO_GRID",
      "data_type" : "VARCHAR2",
      "new_value" : "S",
      "old_value" : null
    }, {
      "column_name" : "IE_RESTRINGE_EMPRESA",
      "data_type" : "VARCHAR2",
      "new_value" : "N",
      "old_value" : null
    }, {
      "column_name" : "QT_MAX_CAMPO",
      "data_type" : "NUMBER",
      "new_value" : "0",
      "old_value" : null
    }, {
      "column_name" : "QT_ALTURA_PANEL",
      "data_type" : "NUMBER",
      "new_value" : "0",
      "old_value" : null
    }, {
      "column_name" : "QT_LARGURA_PANEL",
      "data_type" : "NUMBER",
      "new_value" : "0",
      "old_value" : null
    }, {
      "column_name" : "QT_POS_ESQUERDA",
      "data_type" : "NUMBER",
      "new_value" : "0",
      "old_value" : null
    }, {
      "column_name" : "QT_POS_TOPO",
      "data_type" : "NUMBER",
      "new_value" : "0",
      "old_value" : null
    }, {
      "column_name" : "QT_INTERVALO_CAMPO",
      "data_type" : "NUMBER",
      "new_value" : "0",
      "old_value" : null
    }, {
      "column_name" : "IE_TEMPORARIA",
      "data_type" : "VARCHAR2",
      "new_value" : "N",
      "old_value" : null
    }, {
      "column_name" : "IE_EXPORTAR",
      "data_type" : "VARCHAR2",
      "new_value" : "N",
      "old_value" : null
    }, {
      "column_name" : "IE_REGRA_TABELA",
      "data_type" : "VARCHAR2",
      "new_value" : "N",
      "old_value" : null
    }, {
      "column_name" : "IE_LIMPAR_LOG",
      "data_type" : "VARCHAR2",
      "new_value" : "N",
      "old_value" : null
    }, {
      "column_name" : "DT_ATUALIZACAO_NREC",
      "data_type" : "DATE",
      "new_value" : "27/06/2018 09:33:32",
      "old_value" : null
    }, {
      "column_name" : "NM_USUARIO_NREC",
      "data_type" : "VARCHAR2",
      "new_value" : "srcunha",
      "old_value" : null
    }, {
      "column_name" : "IE_CALLSTACK",
      "data_type" : "VARCHAR2",
      "new_value" : "N",
      "old_value" : null
    }, {
      "column_name" : "CD_EXP_TITULO",
      "data_type" : "NUMBER",
      "new_value" : 0,
      "old_value" : null
    }, {
      "column_name" : "CD_EXP_CADASTRO",
      "data_type" : "NUMBER",
      "new_value" : 886182,
      "old_value" : null
    }, {
      "column_name" : "CD_EXP_TABELA",
      "data_type" : "NUMBER",
      "new_value" : 886183,
      "old_value" : null
    }, {
      "column_name" : "IE_CRIA_LOG_LOCAL",
      "data_type" : "VARCHAR2",
      "new_value" : "",
      "old_value" : null
    }, {
      "column_name" : "DS_LAYER",
      "data_type" : "VARCHAR2",
      "new_value" : "CORE.CMDK_LTDA",
      "old_value" : null
    } ]
  }, {
    "event_info" : {
      "date" : "29/08/2025 13:17:07",
      "sequence" : 500010,
      "date_format" : "dd/mm/rrrr hh24:mi:ss",
      "dml_operation" : "INSERT",
      "table_name" : "TABELA_ATRIBUTO",
      "tag_name" : "CMDK",
      "tasy_user" : "lpfreitas",
      "guid" : "79dd5dd4-aa65-4892-a67d-0bb81160cd3f"
    },
    "server_info" : {
      "charset" : "AMERICAN_AMERICA.AL32UTF8",
      "database_version" : "19.0",
      "instance_name" : "phcdb4"
    },
    "session_info" : {
      "machine" : "55571289ae56",
      "os_user" : "root",
      "tasy_user" : "lpfreitas"
    },
    "primary_key_values" : [ {
      "column_name" : "NM_TABELA",
      "data_type" : "VARCHAR2",
      "new_value" : "CMDKLTD_AAZFMED_50",
      "old_value" : null
    }, {
      "column_name" : "NM_ATRIBUTO",
      "data_type" : "VARCHAR2",
      "new_value" : "C_NR_SEQUENCIA",
      "old_value" : null
    } ],
    "column_values" : [ {
      "column_name" : "NR_SEQUENCIA_CRIACAO",
      "data_type" : "NUMBER",
      "new_value" : 1,
      "old_value" : null
    }, {
      "column_name" : "IE_OBRIGATORIO",
      "data_type" : "VARCHAR2",
      "new_value" : "S",
      "old_value" : null
    }, {
      "column_name" : "NM_USUARIO",
      "data_type" : "VARCHAR2",
      "new_value" : "lpfreitas",
      "old_value" : null
    }, {
      "column_name" : "QT_DECIMAIS",
      "data_type" : "NUMBER",
      "new_value" : 0,
      "old_value" : null
    }, {
      "column_name" : "IE_CRIAR_ALTERAR",
      "data_type" : "VARCHAR2",
      "new_value" : "M",
      "old_value" : null
    }, {
      "column_name" : "IE_SITUACAO",
      "data_type" : "VARCHAR2",
      "new_value" : "A",
      "old_value" : null
    }, {
      "column_name" : "VL_DEFAULT",
      "data_type" : "VARCHAR2",
      "new_value" : "",
      "old_value" : null
    }, {
      "column_name" : "NM_ATRIBUTO",
      "data_type" : "VARCHAR2",
      "new_value" : "C_NR_SEQUENCIA",
      "old_value" : null
    }, {
      "column_name" : "IE_LOG_EXCLUSAO",
      "data_type" : "VARCHAR2",
      "new_value" : "N",
      "old_value" : null
    }, {
      "column_name" : "QT_TAMANHO",
      "data_type" : "NUMBER",
      "new_value" : 10,
      "old_value" : null
    }, {
      "column_name" : "NM_TABELA",
      "data_type" : "VARCHAR2",
      "new_value" : "CMDKLTD_AAZFMED_50",
      "old_value" : null
    }, {
      "column_name" : "CD_DOMINIO",
      "data_type" : "NUMBER",
      "new_value" : 0,
      "old_value" : null
    }, {
      "column_name" : "DT_CRIACAO",
      "data_type" : "DATE",
      "new_value" : "27/06/2018 09:33:34",
      "old_value" : null
    }, {
      "column_name" : "IE_CRIAR_DESCRICAO",
      "data_type" : "VARCHAR2",
      "new_value" : "N",
      "old_value" : null
    }, {
      "column_name" : "NM_ATRIBUTO_PAI",
      "data_type" : "VARCHAR2",
      "new_value" : "",
      "old_value" : null
    }, {
      "column_name" : "QT_SEQ_INICIO",
      "data_type" : "NUMBER",
      "new_value" : 1,
      "old_value" : null
    }, {
      "column_name" : "QT_SEQ_INCREMENTO",
      "data_type" : "NUMBER",
      "new_value" : 1,
      "old_value" : null
    }, {
      "column_name" : "DS_VALORES",
      "data_type" : "VARCHAR2",
      "new_value" : "",
      "old_value" : null
    }, {
      "column_name" : "IE_READONLY",
      "data_type" : "VARCHAR2",
      "new_value" : "N",
      "old_value" : null
    }, {
      "column_name" : "IE_TABSTOP",
      "data_type" : "VARCHAR2",
      "new_value" : "S",
      "old_value" : null
    }, {
      "column_name" : "DT_ATUALIZACAO",
      "data_type" : "DATE",
      "new_value" : "25/08/2025 17:39:51",
      "old_value" : null
    }, {
      "column_name" : "IE_TIPO_ATRIBUTO",
      "data_type" : "VARCHAR2",
      "new_value" : "NUMBER",
      "old_value" : null
    }, {
      "column_name" : "IE_CONVERTE_NEGATIVO",
      "data_type" : "VARCHAR2",
      "new_value" : "N",
      "old_value" : null
    }, {
      "column_name" : "QT_CACHE",
      "data_type" : "NUMBER",
      "new_value" : 0,
      "old_value" : null
    }, {
      "column_name" : "IE_LOG_UPDATE",
      "data_type" : "VARCHAR2",
      "new_value" : "N",
      "old_value" : null
    }, {
      "column_name" : "IE_ATUALIZAR_VERSAO",
      "data_type" : "VARCHAR2",
      "new_value" : "N",
      "old_value" : null
    }, {
      "column_name" : "IE_STATUS",
      "data_type" : "VARCHAR2",
      "new_value" : "N",
      "old_value" : null
    }, {
      "column_name" : "IE_CRIAR_DESC_FK",
      "data_type" : "VARCHAR2",
      "new_value" : "S",
      "old_value" : null
    }, {
      "column_name" : "IE_UNIDADE_MEDIDA",
      "data_type" : "VARCHAR2",
      "new_value" : "S",
      "old_value" : null
    }, {
      "column_name" : "IE_REGRA_UNID_MEDIDA",
      "data_type" : "VARCHAR2",
      "new_value" : "N",
      "old_value" : null
    }, {
      "column_name" : "IE_DBL_CLICK_READONLY",
      "data_type" : "VARCHAR2",
      "new_value" : "N",
      "old_value" : null
    }, {
      "column_name" : "IE_DEFAULT_BANCO",
      "data_type" : "VARCHAR2",
      "new_value" : "N",
      "old_value" : null
    }, {
      "column_name" : "CD_EXP_DESC",
      "data_type" : "NUMBER",
      "new_value" : 557610,
      "old_value" : null
    }, {
      "column_name" : "CD_EXP_VALORES",
      "data_type" : "NUMBER",
      "new_value" : 0,
      "old_value" : null
    }, {
      "column_name" : "NR_SEQ_DIC_OBJETO",
      "data_type" : "NUMBER",
      "new_value" : 0,
      "old_value" : null
    }, {
      "column_name" : "IE_INFORMACAO_SENSIVEL",
      "data_type" : "VARCHAR2",
      "new_value" : "",
      "old_value" : null
    } ]
  }, {
    "event_info" : {
      "date" : "29/08/2025 13:17:07",
      "sequence" : 500011,
      "date_format" : "dd/mm/rrrr hh24:mi:ss",
      "dml_operation" : "INSERT",
      "table_name" : "INDICE",
      "tag_name" : "CMDK",
      "tasy_user" : "lpfreitas",
      "guid" : "42c7aeb7-c702-45b1-b3b4-f30edfeb02ef"
    },
    "server_info" : {
      "charset" : "AMERICAN_AMERICA.AL32UTF8",
      "database_version" : "19.0",
      "instance_name" : "phcdb4"
    },
    "session_info" : {
      "machine" : "55571289ae56",
      "os_user" : "root",
      "tasy_user" : "lpfreitas"
    },
    "primary_key_values" : [ {
      "column_name" : "NM_TABELA",
      "data_type" : "VARCHAR2",
      "new_value" : "CMDKLTD_AAZFMED_50",
      "old_value" : null
    }, {
      "column_name" : "NM_INDICE",
      "data_type" : "VARCHAR2",
      "new_value" : "AAZFMED_50_PK",
      "old_value" : null
    } ],
    "column_values" : [ {
      "column_name" : "DS_INDICE",
      "data_type" : "VARCHAR2",
      "new_value" : "Chave prim\u00e1ria",
      "old_value" : null
    }, {
      "column_name" : "IE_TIPO",
      "data_type" : "VARCHAR2",
      "new_value" : "PK",
      "old_value" : null
    }, {
      "column_name" : "NM_USUARIO",
      "data_type" : "VARCHAR2",
      "new_value" : "lpfreitas",
      "old_value" : null
    }, {
      "column_name" : "DT_CRIACAO",
      "data_type" : "DATE",
      "new_value" : "27/06/2018 09:33:41",
      "old_value" : null
    }, {
      "column_name" : "IE_SITUACAO",
      "data_type" : "VARCHAR2",
      "new_value" : "A",
      "old_value" : null
    }, {
      "column_name" : "NM_INDICE",
      "data_type" : "VARCHAR2",
      "new_value" : "AAZFMED_50_PK",
      "old_value" : null
    }, {
      "column_name" : "NM_TABELA",
      "data_type" : "VARCHAR2",
      "new_value" : "CMDKLTD_AAZFMED_50",
      "old_value" : null
    }, {
      "column_name" : "IE_CRIAR_ALTERAR",
      "data_type" : "VARCHAR2",
      "new_value" : "M",
      "old_value" : null
    }, {
      "column_name" : "DT_ATUALIZACAO",
      "data_type" : "DATE",
      "new_value" : "25/08/2025 17:39:51",
      "old_value" : null
    }, {
      "column_name" : "IE_IGNORADO_CLIENTE",
      "data_type" : "VARCHAR2",
      "new_value" : "",
      "old_value" : null
    }, {
      "column_name" : "IE_CLASSIFICACAO",
      "data_type" : "VARCHAR2",
      "new_value" : "IR",
      "old_value" : null
    } ]
  }, {
    "event_info" : {
      "date" : "29/08/2025 13:17:07",
      "sequence" : 500012,
      "date_format" : "dd/mm/rrrr hh24:mi:ss",
      "dml_operation" : "INSERT",
      "table_name" : "INDICE_ATRIBUTO",
      "tag_name" : "CMDK",
      "tasy_user" : "lpfreitas",
      "guid" : "1b21028f-a39e-4533-aa04-e4979ec5a74e"
    },
    "server_info" : {
      "charset" : "AMERICAN_AMERICA.AL32UTF8",
      "database_version" : "19.0",
      "instance_name" : "phcdb4"
    },
    "session_info" : {
      "machine" : "55571289ae56",
      "os_user" : "root",
      "tasy_user" : "lpfreitas"
    },
    "primary_key_values" : [ {
      "column_name" : "NM_TABELA",
      "data_type" : "VARCHAR2",
      "new_value" : "CMDKLTD_AAZFMED_50",
      "old_value" : null
    }, {
      "column_name" : "NM_INDICE",
      "data_type" : "VARCHAR2",
      "new_value" : "AAZFMED_50_PK",
      "old_value" : null
    }, {
      "column_name" : "NR_SEQUENCIA",
      "data_type" : "NUMBER",
      "new_value" : 1,
      "old_value" : null
    } ],
    "column_values" : [ {
      "column_name" : "NM_TABELA",
      "data_type" : "VARCHAR2",
      "new_value" : "CMDKLTD_AAZFMED_50",
      "old_value" : null
    }, {
      "column_name" : "DT_ATUALIZACAO",
      "data_type" : "DATE",
      "new_value" : "25/08/2025 17:39:51",
      "old_value" : null
    }, {
      "column_name" : "NM_INDICE",
      "data_type" : "VARCHAR2",
      "new_value" : "AAZFMED_50_PK",
      "old_value" : null
    }, {
      "column_name" : "NR_SEQUENCIA",
      "data_type" : "NUMBER",
      "new_value" : 1,
      "old_value" : null
    }, {
      "column_name" : "NM_USUARIO",
      "data_type" : "VARCHAR2",
      "new_value" : "lpfreitas",
      "old_value" : null
    }, {
      "column_name" : "NM_ATRIBUTO",
      "data_type" : "VARCHAR2",
      "new_value" : "C_NR_SEQUENCIA",
      "old_value" : null
    }, {
      "column_name" : "DS_INDICE_FUNCTION",
      "data_type" : "VARCHAR2",
      "new_value" : "",
      "old_value" : null
    } ]
  }, {
    "event_info" : {
      "date" : "29/08/2025 13:17:07",
      "sequence" : 500013,
      "date_format" : "dd/mm/rrrr hh24:mi:ss",
      "dml_operation" : "INSERT",
      "table_name" : "INTEGRIDADE_REFERENCIAL",
      "tag_name" : "CMDK",
      "tasy_user" : "lpfreitas",
      "guid" : "abefad47-4f93-4d55-b0e8-472d7e60bd81"
    },
    "server_info" : {
      "charset" : "AMERICAN_AMERICA.AL32UTF8",
      "database_version" : "19.0",
      "instance_name" : "phcdb4"
    },
    "session_info" : {
      "machine" : "55571289ae56",
      "os_user" : "root",
      "tasy_user" : "lpfreitas"
    },
    "primary_key_values" : [ {
      "column_name" : "NM_TABELA",
      "data_type" : "VARCHAR2",
      "new_value" : "CMDKLTD_AAZFMED_50",
      "old_value" : null
    }, {
      "column_name" : "NM_INTEGRIDADE_REFERENCIAL",
      "data_type" : "VARCHAR2",
      "new_value" : "AAZFMED6E7_AAZFMED_FK",
      "old_value" : null
    } ],
    "column_values" : [ {
      "column_name" : "IE_REGRA_DELECAO",
      "data_type" : "VARCHAR2",
      "new_value" : "CASCADE",
      "old_value" : null
    }, {
      "column_name" : "NM_TABELA",
      "data_type" : "VARCHAR2",
      "new_value" : "CMDKLTD_AAZFMED_50",
      "old_value" : null
    }, {
      "column_name" : "DT_ATUALIZACAO",
      "data_type" : "DATE",
      "new_value" : "25/08/2025 17:39:51",
      "old_value" : null
    }, {
      "column_name" : "DT_CRIACAO",
      "data_type" : "DATE",
      "new_value" : "25/08/2025 17:39:51",
      "old_value" : null
    }, {
      "column_name" : "IE_CRIAR_ALTERAR",
      "data_type" : "VARCHAR2",
      "new_value" : "I",
      "old_value" : null
    }, {
      "column_name" : "IE_SITUACAO",
      "data_type" : "VARCHAR2",
      "new_value" : "A",
      "old_value" : null
    }, {
      "column_name" : "NM_TABELA_REFERENCIA",
      "data_type" : "VARCHAR2",
      "new_value" : "AAZF_MED",
      "old_value" : null
    }, {
      "column_name" : "NM_USUARIO",
      "data_type" : "VARCHAR2",
      "new_value" : "lpfreitas",
      "old_value" : null
    }, {
      "column_name" : "NM_INTEGRIDADE_REFERENCIAL",
      "data_type" : "VARCHAR2",
      "new_value" : "AAZFMED6E7_AAZFMED_FK",
      "old_value" : null
    } ]
  }, {
    "event_info" : {
      "date" : "29/08/2025 13:17:07",
      "sequence" : 500014,
      "date_format" : "dd/mm/rrrr hh24:mi:ss",
      "dml_operation" : "INSERT",
      "table_name" : "INTEGRIDADE_ATRIBUTO",
      "tag_name" : "CMDK",
      "tasy_user" : "lpfreitas",
      "guid" : "3c0a9a88-a942-4ede-a7da-45809e902a4d"
    },
    "server_info" : {
      "charset" : "AMERICAN_AMERICA.AL32UTF8",
      "database_version" : "19.0",
      "instance_name" : "phcdb4"
    },
    "session_info" : {
      "machine" : "55571289ae56",
      "os_user" : "root",
      "tasy_user" : "lpfreitas"
    },
    "primary_key_values" : [ {
      "column_name" : "NM_TABELA",
      "data_type" : "VARCHAR2",
      "new_value" : "CMDKLTD_AAZFMED_50",
      "old_value" : null
    }, {
      "column_name" : "NM_INTEGRIDADE_REFERENCIAL",
      "data_type" : "VARCHAR2",
      "new_value" : "AAZFMED6E7_AAZFMED_FK",
      "old_value" : null
    }, {
      "column_name" : "NM_ATRIBUTO",
      "data_type" : "VARCHAR2",
      "new_value" : "C_NR_SEQUENCIA",
      "old_value" : null
    } ],
    "column_values" : [ {
      "column_name" : "NM_ATRIBUTO_REF",
      "data_type" : "VARCHAR2",
      "new_value" : "C_NR_SEQUENCIA",
      "old_value" : null
    }, {
      "column_name" : "NM_TABELA",
      "data_type" : "VARCHAR2",
      "new_value" : "CMDKLTD_AAZFMED_50",
      "old_value" : null
    }, {
      "column_name" : "NM_INTEGRIDADE_REFERENCIAL",
      "data_type" : "VARCHAR2",
      "new_value" : "AAZFMED6E7_AAZFMED_FK",
      "old_value" : null
    }, {
      "column_name" : "NM_ATRIBUTO",
      "data_type" : "VARCHAR2",
      "new_value" : "C_NR_SEQUENCIA",
      "old_value" : null
    }, {
      "column_name" : "DT_ATUALIZACAO",
      "data_type" : "DATE",
      "new_value" : "25/08/2025 17:39:51",
      "old_value" : null
    }, {
      "column_name" : "NM_USUARIO",
      "data_type" : "VARCHAR2",
      "new_value" : "lpfreitas",
      "old_value" : null
    }, {
      "column_name" : "IE_SEQUENCIA_CRIACAO",
      "data_type" : "NUMBER",
      "new_value" : 1,
      "old_value" : null
    } ]
  }, {
    "event_info" : {
      "date" : "29/08/2025 13:17:07",
      "sequence" : 500015,
      "date_format" : "dd/mm/rrrr hh24:mi:ss",
      "dml_operation" : "INSERT",
      "table_name" : "TABELA_ATRIBUTO_CUSTOM",
      "tag_name" : "CMDK",
      "tasy_user" : "lpfreitas",
      "guid" : "9dfbef5a-3edd-4579-97d1-89a456efd12d"
    },
    "server_info" : {
      "charset" : "AMERICAN_AMERICA.AL32UTF8",
      "database_version" : "19.0",
      "instance_name" : "phcdb4"
    },
    "session_info" : {
      "machine" : "55571289ae56",
      "os_user" : "root",
      "tasy_user" : "lpfreitas"
    },
    "primary_key_values" : [ {
      "column_name" : "NM_TABELA",
      "data_type" : "VARCHAR2",
      "new_value" : "AAZF_MED",
      "old_value" : null
    }, {
      "column_name" : "NM_ATRIBUTO",
      "data_type" : "VARCHAR2",
      "new_value" : "DADADA",
      "old_value" : null
    } ],
    "column_values" : [ {
      "column_name" : "IE_TIPO_ATRIBUTO",
      "data_type" : "VARCHAR2",
      "new_value" : "VARCHAR2",
      "old_value" : null
    }, {
      "column_name" : "GUID_EXTENSION",
      "data_type" : "VARCHAR2",
      "new_value" : "6e7c4f4c-a8fd-48bd-ba6b-3d2998823481",
      "old_value" : null
    }, {
      "column_name" : "NM_TABLE_REF",
      "data_type" : "VARCHAR2",
      "new_value" : "CMDKLTD_AAZFMED_50",
      "old_value" : null
    }, {
      "column_name" : "IE_OBRIGATORIO",
      "data_type" : "VARCHAR2",
      "new_value" : "N",
      "old_value" : null
    }, {
      "column_name" : "DT_ATUALIZACAO",
      "data_type" : "DATE",
      "new_value" : "25/08/2025 17:39:51",
      "old_value" : null
    }, {
      "column_name" : "NM_USUARIO",
      "data_type" : "VARCHAR2",
      "new_value" : "lpfreitas",
      "old_value" : null
    }, {
      "column_name" : "NR_SEQUENCIA_CRIACAO",
      "data_type" : "NUMBER",
      "new_value" : 2,
      "old_value" : null
    }, {
      "column_name" : "NM_ATRIBUTO",
      "data_type" : "VARCHAR2",
      "new_value" : "DADADA",
      "old_value" : null
    }, {
      "column_name" : "QT_TAMANHO",
      "data_type" : "NUMBER",
      "new_value" : 255,
      "old_value" : null
    }, {
      "column_name" : "NM_TABELA",
      "data_type" : "VARCHAR2",
      "new_value" : "AAZF_MED",
      "old_value" : null
    } ]
  }, {
    "event_info" : {
      "date" : "29/08/2025 13:17:07",
      "sequence" : 500016,
      "date_format" : "dd/mm/rrrr hh24:mi:ss",
      "dml_operation" : "INSERT",
      "table_name" : "TABELA_ATRIBUTO",
      "tag_name" : "CMDK",
      "tasy_user" : "lpfreitas",
      "guid" : "9446ea86-4e16-46db-98d9-786fdc9495e3"
    },
    "server_info" : {
      "charset" : "AMERICAN_AMERICA.AL32UTF8",
      "database_version" : "19.0",
      "instance_name" : "phcdb4"
    },
    "session_info" : {
      "machine" : "55571289ae56",
      "os_user" : "root",
      "tasy_user" : "lpfreitas"
    },
    "primary_key_values" : [ {
      "column_name" : "NM_TABELA",
      "data_type" : "VARCHAR2",
      "new_value" : "CMDKLTD_AAZFMED_50",
      "old_value" : null
    }, {
      "column_name" : "NM_ATRIBUTO",
      "data_type" : "VARCHAR2",
      "new_value" : "DADADA",
      "old_value" : null
    } ],
    "column_values" : [ {
      "column_name" : "NR_SEQUENCIA_CRIACAO",
      "data_type" : "NUMBER",
      "new_value" : 31,
      "old_value" : null
    }, {
      "column_name" : "IE_OBRIGATORIO",
      "data_type" : "VARCHAR2",
      "new_value" : "N",
      "old_value" : null
    }, {
      "column_name" : "NM_USUARIO",
      "data_type" : "VARCHAR2",
      "new_value" : "lpfreitas",
      "old_value" : null
    }, {
      "column_name" : "IE_CRIAR_ALTERAR",
      "data_type" : "VARCHAR2",
      "new_value" : "M",
      "old_value" : null
    }, {
      "column_name" : "IE_SITUACAO",
      "data_type" : "VARCHAR2",
      "new_value" : "A",
      "old_value" : null
    }, {
      "column_name" : "NM_ATRIBUTO",
      "data_type" : "VARCHAR2",
      "new_value" : "DADADA",
      "old_value" : null
    }, {
      "column_name" : "IE_LOG_EXCLUSAO",
      "data_type" : "VARCHAR2",
      "new_value" : "S",
      "old_value" : null
    }, {
      "column_name" : "QT_TAMANHO",
      "data_type" : "NUMBER",
      "new_value" : 255,
      "old_value" : null
    }, {
      "column_name" : "NM_TABELA",
      "data_type" : "VARCHAR2",
      "new_value" : "CMDKLTD_AAZFMED_50",
      "old_value" : null
    }, {
      "column_name" : "DT_CRIACAO",
      "data_type" : "DATE",
      "new_value" : "25/08/2025 17:39:51",
      "old_value" : null
    }, {
      "column_name" : "IE_CRIAR_DESCRICAO",
      "data_type" : "VARCHAR2",
      "new_value" : "N",
      "old_value" : null
    }, {
      "column_name" : "DS_VALORES",
      "data_type" : "VARCHAR2",
      "new_value" : "12L",
      "old_value" : null
    }, {
      "column_name" : "IE_READONLY",
      "data_type" : "VARCHAR2",
      "new_value" : "N",
      "old_value" : null
    }, {
      "column_name" : "IE_TABSTOP",
      "data_type" : "VARCHAR2",
      "new_value" : "S",
      "old_value" : null
    }, {
      "column_name" : "DT_ATUALIZACAO",
      "data_type" : "DATE",
      "new_value" : "25/08/2025 17:39:51",
      "old_value" : null
    }, {
      "column_name" : "IE_TIPO_ATRIBUTO",
      "data_type" : "VARCHAR2",
      "new_value" : "VARCHAR2",
      "old_value" : null
    }, {
      "column_name" : "IE_CONVERTE_NEGATIVO",
      "data_type" : "VARCHAR2",
      "new_value" : "N",
      "old_value" : null
    }, {
      "column_name" : "IE_LOG_UPDATE",
      "data_type" : "VARCHAR2",
      "new_value" : "N",
      "old_value" : null
    }, {
      "column_name" : "IE_ATUALIZAR_VERSAO",
      "data_type" : "VARCHAR2",
      "new_value" : "N",
      "old_value" : null
    }, {
      "column_name" : "IE_STATUS",
      "data_type" : "VARCHAR2",
      "new_value" : "N",
      "old_value" : null
    }, {
      "column_name" : "IE_CRIAR_DESC_FK",
      "data_type" : "VARCHAR2",
      "new_value" : "S",
      "old_value" : null
    }, {
      "column_name" : "IE_UNIDADE_MEDIDA",
      "data_type" : "VARCHAR2",
      "new_value" : "S",
      "old_value" : null
    }, {
      "column_name" : "IE_REGRA_UNID_MEDIDA",
      "data_type" : "VARCHAR2",
      "new_value" : "N",
      "old_value" : null
    }, {
      "column_name" : "IE_DBL_CLICK_READONLY",
      "data_type" : "VARCHAR2",
      "new_value" : "N",
      "old_value" : null
    }, {
      "column_name" : "IE_DEFAULT_BANCO",
      "data_type" : "VARCHAR2",
      "new_value" : "N",
      "old_value" : null
    }, {
      "column_name" : "CD_EXP_DESC",
      "data_type" : "NUMBER",
      "new_value" : 557610,
      "old_value" : null
    }, {
      "column_name" : "IE_INFORMACAO_SENSIVEL",
      "data_type" : "VARCHAR2",
      "new_value" : "N",
      "old_value" : null
    } ]
  } ]
}